bm2bbox/__init__.py
bm2bbox/main.py
bm2bbox-1.0.4.dist-info/LICENSE
bm2bbox-1.0.4.dist-info/METADATA
bm2bbox-1.0.4.dist-info/WHEEL
bm2bbox-1.0.4.dist-info/entry_points.txt
bm2bbox-1.0.4.dist-info/top_level.txt
bm2bbox-1.0.4.dist-info/RECORD
