Metadata-Version: 2.1
Name: bm2bbox
Version: 1.0.4
Summary: Converts binary mask files to geojson files containing bounding boxes
Author: Juraj Zvolenský
Author-email: Juraj Zvolensky <juro.zvolensky@gmail.com>
Maintainer-email: Juraj Zvolensky <juro.zvolensky@gmail.com>
Keywords: geojson,bounding box,binary mask,image segmentation,object detection,computer vision
Classifier: Development Status :: 5 - Production/Stable
Classifier: Intended Audience :: Science/Research
Requires-Python: >=3.10
License-File: LICENSE
Requires-Dist: geojson >=3.0.1
Requires-Dist: iniconfig >=2.0.0
Requires-Dist: numpy >=1.25.2
Requires-Dist: opencv-python >=4.8.0
Requires-Dist: packaging >=23.1
Requires-Dist: pluggy >=1.3.0
Requires-Dist: pytest >=7.4.1
